liveandletdie/__init__.py
liveandletdie-0.0.9.dist-info/LICENSE.txt
liveandletdie-0.0.9.dist-info/METADATA
liveandletdie-0.0.9.dist-info/WHEEL
liveandletdie-0.0.9.dist-info/top_level.txt
liveandletdie-0.0.9.dist-info/RECORD
