Metadata-Version: 2.1
Name: liveandletdie
Version: 0.0.9
Summary: Simplifies launching and terminating of web development servers from BDD and functional tests.
Home-page: http://github.com/peterhudec/liveandletdie
Author: Peter Hudec
Author-email: peterhudec@peterhudec.com
Maintainer: Authomatic Project Community
Maintainer-email: authomaticproject@protonmail.com
License: MIT
Keywords: Flask,Pyramid,Django,Google App Engine,GAE,BDD,TDD,functional testing,live server
Classifier: Development Status :: 3 - Alpha
Classifier: Environment :: Web Environment
Classifier: Intended Audience :: Developers
Classifier: License :: OSI Approved :: MIT License
Classifier: Operating System :: OS Independent
Classifier: Programming Language :: Python :: 3.7
Classifier: Programming Language :: Python :: 3.8
Classifier: Programming Language :: Python :: 3.9
Classifier: Programming Language :: Python :: 3.10
Classifier: Programming Language :: Python :: 3.11
Classifier: Programming Language :: JavaScript
Classifier: Topic :: Internet :: WWW/HTTP
Classifier: Topic :: Internet :: WWW/HTTP :: Dynamic Content :: CGI Tools/Libraries
Classifier: Topic :: Software Development :: Libraries
Classifier: Topic :: Software Development :: Libraries :: Python Modules
License-File: LICENSE.txt
Requires-Dist: requests
Requires-Dist: werkzeug
